{
    "id": 232,
    "title": "Wonder Woman 1984",
    "poster": "wonder_woman_2",
    "trailer": "sfM7_JLk-84",
    "genres": [
        "Adventures",
        "Fantasy"
    ],
    "production": [
        "Warner Bros. Pictures",
        "DC Entertainment"
    ],
    "director": "Patty Jenkins",
    "producers": "Gal Gadot, Patty Jenkins, Charles Roven, Stephen Jones, Deborah Snyder, Zack Snyder",
    "writtens": "Patty Jenkins, Geoff Johns, Dave Callaham",
    "music": "Hans Zimmer",
    "cinema": "Matthew Jensen",
    "year": 2020,
    "time": 151,
    "countries": [
        "USA",
        "UK",
        "Spain"
    ],
    "budget": {
        "value": 200,
        "suffix": "million"
    },
    "boxoffice": {
        "value": 132,
        "suffix": "million"
    },
    "actors": [
        {
            "name": "Gal Gadot",
            "character": {
                "name": "Diana Prince / Wonder Woman",
                "poster": "wonder-woman"
            }
        },
        {
            "name": "Chris Pine",
            "character": {
                "name": "Steve Trevor",
                "poster": "trevor"
            }
        },
        {
            "name": "Kristen Wiig",
            "character": {
                "name": "Barbara Minerva",
                "poster": "minerva"
            }
        },
        {
            "name": "Pedro Pascal",
            "character": {
                "name": "Maxwell Lord",
                "poster": "lord"
            }
        },
        {
            "name": "Lucian Perez",
            "character": {
                "name": "Alistair"
            }
        }
    ],
    "synopsis": "Diana must contend with a work colleague and businessman, whose desire for extreme wealth sends the world down a path of destruction, after an ancient artifact that grants wishes goes missing.",
    "parts": {
        "title": "DC Extended Universe",
        "part": 9
    },
    "type": "Film",
    "sort": 202012
}
